lectio/__init__.py
lectio/_auth.py
lectio/_beskeder.py
lectio/_dokumenter.py
lectio/_eksamener.py
lectio/_filer.py
lectio/_forside.py
lectio/_fravær.py
lectio/_informationer.py
lectio/_karakterer.py
lectio/_ledigeLokaler.py
lectio/_lektier.py
lectio/_modul.py
lectio/_opgaver.py
lectio/_skema.py
lectio/_spørgeskema.py
lectio/_studieplan.py
lectio/_studieretning.py
lectio/_termin.py
lectio/_utils.py
lectio/imports.py
lectio/lectio.py
python_lectio-1.31.0.dist-info/METADATA
python_lectio-1.31.0.dist-info/WHEEL
python_lectio-1.31.0.dist-info/top_level.txt
python_lectio-1.31.0.dist-info/RECORD
