Metadata-Version: 2.1
Name: python-lectio
Version: 1.31.0
Summary: En SDK til gymnasie siden Lectio
Home-page: https://github.com/jona799t/python-lectio
Author: jona799t
Keywords: python,lectio,sdk,gymnasie,gymnasium
Classifier: Development Status :: 1 - Planning
Classifier: Intended Audience :: Developers
Classifier: Programming Language :: Python :: 3
Classifier: Operating System :: Unix
Classifier: Operating System :: MacOS :: MacOS X
Classifier: Operating System :: Microsoft :: Windows
Requires-Dist: requests
Requires-Dist: beautifulsoup4
Requires-Dist: markdownify
